gstin/__init__.py
gstin/app.py
gstin-0.3.dist-info/LICENSE.txt
gstin-0.3.dist-info/METADATA
gstin-0.3.dist-info/WHEEL
gstin-0.3.dist-info/top_level.txt
gstin-0.3.dist-info/RECORD
