Metadata-Version: 2.1
Name: gstin
Version: 0.3
Summary: Package to retrieve INDIA PAN from GSTIN
Home-page: UNKNOWN
Author: Rashmi Rao
License: MIT
Platform: UNKNOWN
License-File: LICENSE.txt
